sphinxcontrib_lilypond-1.0.0-py3.6-nspkg.pth
sphinxcontrib/lilypond.py
sphinxcontrib_lilypond-1.0.0.dist-info/DESCRIPTION.rst
sphinxcontrib_lilypond-1.0.0.dist-info/METADATA
sphinxcontrib_lilypond-1.0.0.dist-info/RECORD
sphinxcontrib_lilypond-1.0.0.dist-info/WHEEL
sphinxcontrib_lilypond-1.0.0.dist-info/metadata.json
sphinxcontrib_lilypond-1.0.0.dist-info/namespace_packages.txt
sphinxcontrib_lilypond-1.0.0.dist-info/top_level.txt
