Metadata-Version: 2.0
Name: sphinxcontrib-lilypond
Version: 1.0.0
Summary: Sphinx lilypond extension
Home-page: https://github.com/FabriceSalvaire/sphinx-lilypond
Author: Fabrice Salvaire
Author-email: fabrice.salvaire@orange.fr
License: BSD
Download-URL: http://pypi.python.org/pypi/sphinxcontrib-lilypond
Keywords: sphinx extension literalinclude
Platform: any
Classifier: Development Status :: 5 - Production/Stable
Classifier: Environment :: Console
Classifier: Environment :: Web Environment
Classifier: Intended Audience :: Developers
Classifier: License :: OSI Approved :: BSD License
Classifier: Operating System :: OS Independent
Classifier: Programming Language :: Python
Classifier: Topic :: Documentation
Classifier: Topic :: Software Development :: Documentation
Classifier: Topic :: Utilities
Requires-Dist: Sphinx (>=0.6)
